mkdocs_windmill_dark/404.html
mkdocs_windmill_dark/__init__.py
mkdocs_windmill_dark/article-nav.html
mkdocs_windmill_dark/base.html
mkdocs_windmill_dark/main.html
mkdocs_windmill_dark/mkdocs_theme.yml
mkdocs_windmill_dark/nav-item.html
mkdocs_windmill_dark/nav-pane.html
mkdocs_windmill_dark/page-nav-urls.html
mkdocs_windmill_dark/repo-icon.html
mkdocs_windmill_dark/search.html
mkdocs_windmill_dark/topbar.html
mkdocs_windmill_dark/css/base.css
mkdocs_windmill_dark/css/bootstrap-3.3.7.css
mkdocs_windmill_dark/css/bootstrap-3.3.7.min.css
mkdocs_windmill_dark/css/font-awesome-4.7.0.css
mkdocs_windmill_dark/css/font-awesome-4.7.0.min.css
mkdocs_windmill_dark/css/highlight.css
mkdocs_windmill_dark/fonts/fontawesome-webfont.eot
mkdocs_windmill_dark/fonts/fontawesome-webfont.svg
mkdocs_windmill_dark/fonts/fontawesome-webfont.ttf
mkdocs_windmill_dark/fonts/fontawesome-webfont.woff
mkdocs_windmill_dark/fonts/fontawesome-webfont.woff2
mkdocs_windmill_dark/fonts/glyphicons-halflings-regular.eot
mkdocs_windmill_dark/fonts/glyphicons-halflings-regular.svg
mkdocs_windmill_dark/fonts/glyphicons-halflings-regular.ttf
mkdocs_windmill_dark/fonts/glyphicons-halflings-regular.woff
mkdocs_windmill_dark/fonts/glyphicons-halflings-regular.woff2
mkdocs_windmill_dark/img/favicon.ico
mkdocs_windmill_dark/js/base.js
mkdocs_windmill_dark/js/bootstrap-3.3.7.js
mkdocs_windmill_dark/js/bootstrap-3.3.7.min.js
mkdocs_windmill_dark/js/elasticlunr.js
mkdocs_windmill_dark/js/elasticlunr.min.js
mkdocs_windmill_dark/js/highlight.pack.js
mkdocs_windmill_dark/js/jquery-3.2.1.js
mkdocs_windmill_dark/js/jquery-3.2.1.min.js
mkdocs_windmill_dark-0.2.0.dist-info/LICENSE
mkdocs_windmill_dark-0.2.0.dist-info/METADATA
mkdocs_windmill_dark-0.2.0.dist-info/WHEEL
mkdocs_windmill_dark-0.2.0.dist-info/entry_points.txt
mkdocs_windmill_dark-0.2.0.dist-info/top_level.txt
mkdocs_windmill_dark-0.2.0.dist-info/RECORD
