Metadata-Version: 1.1
Name: mkdocs-windmill-dark
Version: 0.2.0
Summary: MkDocs dark theme focused on navigation and usability
Home-page: https://github.com/noraj1337/mkdocs-windmill-dark
Author: Alexandre ZANNI
Author-email: alexandre.zanni@engineer.com
License: MIT
Platform: UNKNOWN
Classifier: Development Status :: 5 - Production/Stable
Classifier: License :: OSI Approved :: MIT License
Classifier: Topic :: Documentation
Classifier: Topic :: Text Processing
